mbutil/__init__.py
mbutil/cli.py
mbutil/util.py
smellman_mbutil-0.3.10.dist-info/METADATA
smellman_mbutil-0.3.10.dist-info/WHEEL
smellman_mbutil-0.3.10.dist-info/entry_points.txt
smellman_mbutil-0.3.10.dist-info/licenses/LICENSE.md
smellman_mbutil-0.3.10.dist-info/RECORD
