Metadata-Version: 2.4
Name: smellman-mbutil
Version: 0.3.10
Summary: An importer and exporter for MBTiles
Author-email: Tom MacWright <tom@macwright.org>
Maintainer-email: Taro Matsuzawa <btm@tech.email.ne.jp>
License: Copyright (c), Development Seed  
License-File: LICENSE.md
Keywords: map,mbtiles,tiles
Classifier: License :: OSI Approved :: MIT License
Classifier: Operating System :: OS Independent
Classifier: Programming Language :: Python :: 3
Requires-Python: >=3.8
Requires-Dist: boto3>=1.37.38
